README.txt
buildout.cfg
setup.py
wc/__init__.py
wc.rating.egg-info/PKG-INFO
wc.rating.egg-info/SOURCES.txt
wc.rating.egg-info/dependency_links.txt
wc.rating.egg-info/namespace_packages.txt
wc.rating.egg-info/not-zip-safe
wc.rating.egg-info/requires.txt
wc.rating.egg-info/top_level.txt
wc/rating/README.txt
wc/rating/__init__.py
wc/rating/configure.zcml
wc/rating/interfaces.py
wc/rating/rating.py
wc/rating/tests.py
wc/rating/viewlet.pt
wc/rating/viewlet.py
